eventstore_grpc/__init__.py
eventstore_grpc/client/__init__.py
eventstore_grpc/client/event_store.py
eventstore_grpc/client/gossip.py
eventstore_grpc/client/operations.py
eventstore_grpc/client/persistent.py
eventstore_grpc/client/projections.py
eventstore_grpc/client/streams.py
eventstore_grpc/client/subscriptions.py
eventstore_grpc/client/users.py
eventstore_grpc/constants.py
eventstore_grpc/core/__init__.py
eventstore_grpc/core/auth.py
eventstore_grpc/core/client_base.py
eventstore_grpc/core/settings.py
eventstore_grpc/core/transport.py
eventstore_grpc/discovery.py
eventstore_grpc/event_data.py
eventstore_grpc/gossip/__init__.py
eventstore_grpc/gossip/read.py
eventstore_grpc/operations/__init__.py
eventstore_grpc/operations/merge_indexes.py
eventstore_grpc/operations/resign_node.py
eventstore_grpc/operations/restart_persistent_subscritions.py
eventstore_grpc/operations/set_node_priority.py
eventstore_grpc/operations/shutdown.py
eventstore_grpc/operations/start_scavenge.py
eventstore_grpc/operations/stop_scavenge.py
eventstore_grpc/options/__init__.py
eventstore_grpc/options/base_options.py
eventstore_grpc/options/channel_credential.py
eventstore_grpc/options/client.py
eventstore_grpc/options/connection_type.py
eventstore_grpc/options/discovery.py
eventstore_grpc/options/dns_cluster.py
eventstore_grpc/options/gossip_cluster.py
eventstore_grpc/options/single_node.py
eventstore_grpc/persistent/__init__.py
eventstore_grpc/persistent/create.py
eventstore_grpc/persistent/delete.py
eventstore_grpc/persistent/get_info.py
eventstore_grpc/persistent/list.py
eventstore_grpc/persistent/read.py
eventstore_grpc/persistent/replay_parked.py
eventstore_grpc/persistent/update.py
eventstore_grpc/projections/__init__.py
eventstore_grpc/projections/create_continuous.py
eventstore_grpc/projections/create_one_time.py
eventstore_grpc/projections/create_transient.py
eventstore_grpc/projections/delete.py
eventstore_grpc/projections/disable.py
eventstore_grpc/projections/enable.py
eventstore_grpc-0.1.1.dist-info/LICENSE.md
eventstore_grpc-0.1.1.dist-info/METADATA
eventstore_grpc-0.1.1.dist-info/WHEEL
eventstore_grpc-0.1.1.dist-info/RECORD
