Metadata-Version: 2.1
Name: eventstore-grpc
Version: 0.1.1
Summary: EventStoreDB gRPC client.
Home-page: https://github.com/stefanondisponibile/eventstore_grpc
License: MIT
Author: Stefano Frassetto
Author-email: frassetto.stefano@gmail.com
Maintainer: Stefano Frassetto
Maintainer-email: frassetto.stefano@gmail.com
Requires-Python: >=3.10,<4.0
Classifier: Development Status :: 4 - Beta
Classifier: Intended Audience :: Developers
Classifier: Intended Audience :: Information Technology
Classifier: Intended Audience :: System Administrators
Classifier: License :: OSI Approved :: MIT License
Classifier: Operating System :: OS Independent
Classifier: Programming Language :: Python
Classifier: Programming Language :: Python :: 3
Classifier: Programming Language :: Python :: 3.10
Classifier: Programming Language :: Python :: 3.11
Classifier: Programming Language :: Python :: 3 :: Only
Classifier: Topic :: Database
Classifier: Topic :: Internet
Requires-Dist: grpcio (>=1.54.2,<2.0.0)
Requires-Dist: grpcio-status (>=1.0.0,<2.0.0)
Requires-Dist: protobuf (>=4.21.6,<5.0.0)
Requires-Dist: urllib3 (>=1.26.9,<2.0.0)
Project-URL: Documentation, https://stefanondisponibile.github.io/eventstore_grpc
Project-URL: Repository, https://github.com/stefanondisponibile/eventstore_grpc
